jsonomy/__init__.py
jsonomy/functions.py
jsonomy/jsonomy.py
jsonomy-0.0.3.dist-info/METADATA
jsonomy-0.0.3.dist-info/WHEEL
jsonomy-0.0.3.dist-info/top_level.txt
jsonomy-0.0.3.dist-info/RECORD
