Metadata-Version: 2.1
Name: jsonomy
Version: 0.0.3
Summary: Basic JSON parser, that converts APIs JSON output to be more pythonic, including camel case to snake case conversion, and converting timestamps to datetime objects.
Home-page: https://github.com/lewis-morris/jsonomy
Author: Lewis Morris
Author-email: lewis.morris@gmail.com
License: MIT
Keywords: json parser pythonic camelcase snakecase datetime conversion
Classifier: Development Status :: 3 - Alpha
Classifier: Intended Audience :: Developers
Classifier: Topic :: Software Development :: Libraries
Classifier: License :: OSI Approved :: MIT License
Classifier: Programming Language :: Python :: 3
Classifier: Programming Language :: Python :: 3.9
Requires-Python: >=3.6
